PythonJinjie/README.md
PythonJinjie/__init__.py
PythonJinjie/__main__.py
PythonJinjie/file.epub
PythonJinjie/index.html
PythonJinjie/css/__init__.py
PythonJinjie/css/annotations.css
PythonJinjie/css/main.css
PythonJinjie/css/normalize.css
PythonJinjie/css/popup.css
PythonJinjie/font/__init__.py
PythonJinjie/font/fontello.eot
PythonJinjie/font/fontello.svg
PythonJinjie/font/fontello.ttf
PythonJinjie/font/fontello.woff
PythonJinjie/img/__init__.py
PythonJinjie/img/annotator-glyph-sprite.png
PythonJinjie/img/annotator-icon-sprite.png
PythonJinjie/img/apple-touch-icon.png
PythonJinjie/img/cancelfullscreen.png
PythonJinjie/img/close.png
PythonJinjie/img/fullscreen.png
PythonJinjie/img/loader.gif
PythonJinjie/img/menu-icon.png
PythonJinjie/img/save.png
PythonJinjie/img/saved.png
PythonJinjie/img/settings-s.png
PythonJinjie/img/settings.png
PythonJinjie/img/star.png
PythonJinjie/js/__init__.py
PythonJinjie/js/epub.js
PythonJinjie/js/epub.min.js
PythonJinjie/js/epub.min.map
PythonJinjie/js/hooks.min.js
PythonJinjie/js/hooks.min.map
PythonJinjie/js/reader.js
PythonJinjie/js/reader.js.map
PythonJinjie/js/reader.min.js
PythonJinjie/js/reader.min.map
PythonJinjie/js/hooks/__init__.py
PythonJinjie/js/hooks/extensions/__init__.py
PythonJinjie/js/hooks/extensions/highlight.js
PythonJinjie/js/libs/__init__.py
PythonJinjie/js/libs/jquery.min.js
PythonJinjie/js/libs/localforage.min.js
PythonJinjie/js/libs/screenfull.js
PythonJinjie/js/libs/screenfull.min.js
PythonJinjie/js/libs/zip.min.js
PythonJinjie/js/plugins/__init__.py
PythonJinjie/js/plugins/hypothesis.js
PythonJinjie/js/plugins/search.js
python_jinjie-2024.3.1.0.dist-info/METADATA
python_jinjie-2024.3.1.0.dist-info/WHEEL
python_jinjie-2024.3.1.0.dist-info/entry_points.txt
python_jinjie-2024.3.1.0.dist-info/top_level.txt
python_jinjie-2024.3.1.0.dist-info/RECORD
